ax25
